inheritance_dict/__init__.py
inheritance_dict/_version.py
inheritance_dict-0.5.0.0.dist-info/LICENSE
inheritance_dict-0.5.0.0.dist-info/METADATA
inheritance_dict-0.5.0.0.dist-info/WHEEL
inheritance_dict-0.5.0.0.dist-info/top_level.txt
inheritance_dict-0.5.0.0.dist-info/RECORD
