Metadata-Version: 2.1
Name: inheritance-dict
Version: 0.5.0.0
Summary: Looking for the value associated with the most specific super type in the dictionary
Home-page: https://github.com/hapytex/inheritance_dict/
Author: Willem Van Onsem
Author-email: Willem Van Onsem <yourfriends@hapytex.eu>
License: BSD-3-Clause
Classifier: Intended Audience :: Developers
Classifier: License :: OSI Approved :: BSD License
Classifier: Operating System :: OS Independent
Classifier: Programming Language :: Python
Classifier: Programming Language :: Python :: 3
Classifier: Programming Language :: Python :: 3 :: Only
Classifier: Programming Language :: Python :: 3.10
Classifier: Programming Language :: Python :: 3.11
Classifier: Programming Language :: Python :: 3.12
Requires-Python: >=3.8
License-File: LICENSE
